{"qHG1GYRErxZ/4J4jKkruwQ==":"path44-121x70.png","GPhi77EKOM/EVJYZmnJuhw==":"43514hd-2000x1125.jpg","Y8fOp1TNRlZpkbOYiUyCpw==":"logo-192x163.png","jUhqgQkvp2wyYEbgymBE6A==":"dji_0035%20(1)-516x290.jpg","7+tMinaME2AdWN/FC0Dg7A==":"dji_0035%20(1)-standard-scale-4_00x-gigapixel-2000x1124.jpeg","H8QGmXeesNvXVbuYZ3lb7g==":"dji_0035%20(1)-standard-scale-4_00x-gigapixel-2000x1124.jpeg","ZGi5p+spcMNzbyKBf+LJOA==":"deltapi.svg","TNCCwcb6HcKRqHX33cYM5g==":"path44-96x56.png","Ou+0mcVQT4LZiF/XB/IiEw==":"20180418-1645331512-978x608.jpg","aio11pc7XQAzEaKu6GB/oA==":"20180323-1450341511-506x285.jpg","m+eyEi3abnEfghTCOB41Gg==":"img-20171206-wa00051518-2000x1125.jpg","MrtxEtjkbUgh/yoXAhQ9FA==":"img-20180329-wa00041513-2000x1125.jpg","JftEdiuCSe9XjEjOwon0Fg==":"img-20180422-wa00041515-963x667.jpg","7EKDkqvs87AbNUyagpF3OQ==":"img-20180727-wa00001517-1280x720.jpg","X/uCk1clSM3gwf8D0DP20Q==":"mobirise2020619-13142020-6-0-13-27-34-1280x720.jpg","ZWktQ6ffCREHv39Sg53dwg==":"nhntsy-edited-1014x619.jpg","ZHFFbfy4+jo7A+7KwZkOBA==":"img-20190725-134212-edited-2000x1500.jpg","bM+gxtanDUFGcfHwaDhxCQ==":"encrypto-797x512.jpg","wRmDjO+SQ9OGcfFBf1thjg==":"img-20190828-195917-edited-2000x1047.jpg","B1ZNW1eaexE5bmyjP6eKBw==":"image-1270x587.jpg"}